setup.py
configurati/__init__.py
configurati/attrs.py
configurati/commands.py
configurati/configure.py
configurati/exceptions.py
configurati/globals.py
configurati/interpolate.py
configurati/utils.py
configurati/validation.py
configurati.egg-info/PKG-INFO
configurati.egg-info/SOURCES.txt
configurati.egg-info/dependency_links.txt
configurati.egg-info/requires.txt
configurati.egg-info/top_level.txt
configurati/loaders/__init__.py
configurati/loaders/commandline.py
configurati/loaders/json.py
configurati/loaders/python.py
configurati/loaders/utils.py
configurati/loaders/yaml.py
configurati/loaders/tests/__init__.py
configurati/loaders/tests/test_commandline.py
configurati/loaders/tests/test_json.py
configurati/loaders/tests/test_python.py
configurati/loaders/tests/test_utils.py
configurati/loaders/tests/test_yaml.py