Metadata-Version: 1.1
Name: configurati
Version: 0.2.2
Summary: Configuration files for Python
Home-page: http://github.com/duckworthd/configurati
Author: Daniel Duckworth
Author-email: duckworthd@gmail.com
License: BSD
Keywords: config configuration
Platform: UNKNOWN
Classifier: Development Status :: 4 - Beta
Classifier: Intended Audience :: Developers
Classifier: License :: OSI Approved :: BSD License
Classifier: Operating System :: OS Independent
Classifier: Programming Language :: Python
Classifier: Programming Language :: Python :: Implementation :: CPython
Classifier: Topic :: Software Development :: Libraries
